{
    "Rezeptquelle": "www.maischemalzundmehr.de",
    "ExportVersion": "2.0",
    "Name": "Monroe-Ale",
    "Datum": "13.05.2016",
    "Sorte": "Pale Ale",
    "Autor": "holledauer",
    "Ausschlagwuerze": 20,
    "Stammwuerze": 13.5,
    "Bittere": 30,
    "Farbe": 11,
    "Alkohol": 6,
    "Kurzbeschreibung": "angenehm fruchtiges Pale Ale mit frischen Aromen mit dem Monroe-Hopfen",
    "Malze": [
        {
            "Name": "Pilsner",
            "Menge": 2,
            "Einheit": "kg"
        },
        {
            "Name": "Weizen hell",
            "Menge": 670,
            "Einheit": "g"
        },
        {
            "Name": "Wiener",
            "Menge": 1.33,
            "Einheit": "kg"
        },
        {
            "Name": "Cara Hell",
            "Menge": 170,
            "Einheit": "g"
        }
    ],
    "Maischform": "infusion",
    "Hauptguss": 16.666666666666668,
    "Einmaischtemperatur": 60,
    "Rasten": [
        {
            "Temperatur": 68,
            "Zeit": 75
        }
    ],
    "Abmaischtemperatur": 78,
    "Nachguss": 15,
    "Kochzeit_Wuerze": 70,
    "Hopfenkochen": [
        {
            "Sorte": "Brewers Gold",
            "Menge": 37,
            "Alpha": 5.6,
            "Zeit": 60,
            "Typ": "Standard"
        },
        {
            "Sorte": "Select",
            "Menge": 17,
            "Alpha": 4.3,
            "Zeit": 15,
            "Typ": "Standard"
        }
    ],
    "Stopfhopfen": [
        {
            "Sorte": "Monroe",
            "Menge": 83
        }
    ],
    "Hefe": "US-05",
    "Gaertemperatur": "20",
    "Karbonisierung": 5.5,
    "Anmerkung_Autor": "Nachgu\u00df gesch\u00e4tzt"
}