{
    "Rezeptquelle": "www.maischemalzundmehr.de",
    "ExportVersion": "2.0",
    "Name": "Wolke 5",
    "Datum": "02.08.2016",
    "Sorte": "Alkoholfreies\/-armes",
    "Autor": "Gartenbrauer",
    "Ausschlagwuerze": 20,
    "Stammwuerze": 9.5,
    "Bittere": 18,
    "Farbe": 30,
    "Alkohol": 3.1,
    "Kurzbeschreibung": "Wolke 5? - Wolke 7 ist schon besetzt.\r\nLeichtbier mit viel Geschmack, nicht als Leichtbier erkennbar. Durch die Verwendung der niedrig verg\u00e4renden Windsor-Hefe sehr s\u00fcffig.\r\nMein bisher bestes Leichtbier.",
    "Malze": [
        {
            "Name": "Pilsener",
            "Menge": 1.15,
            "Einheit": "kg"
        },
        {
            "Name": "M\u00fcnchener",
            "Menge": 1.15,
            "Einheit": "kg"
        },
        {
            "Name": "Roggenmalz",
            "Menge": 570,
            "Einheit": "g"
        },
        {
            "Name": "Cararoma",
            "Menge": 57,
            "Einheit": "g"
        },
        {
            "Name": "Pale Chocolate",
            "Menge": 57,
            "Einheit": "g"
        }
    ],
    "Maischform": "infusion",
    "Hauptguss": 13.793103448275863,
    "Einmaischtemperatur": 57,
    "Rasten": [
        {
            "Temperatur": 57,
            "Zeit": 10
        },
        {
            "Temperatur": 64,
            "Zeit": 10
        },
        {
            "Temperatur": 72,
            "Zeit": 30
        },
        {
            "Temperatur": 76,
            "Zeit": 10
        },
        {
            "Temperatur": 78,
            "Zeit": 0
        }
    ],
    "Abmaischtemperatur": 78,
    "Nachguss": 6.32183908045977,
    "Kochzeit_Wuerze": 90,
    "Hopfenkochen": [
        {
            "Sorte": "Magnum",
            "Menge": 8,
            "Alpha": 12.4,
            "Zeit": 80,
            "Typ": "Standard"
        },
        {
            "Sorte": "Huell Melon",
            "Menge": 7,
            "Alpha": 6.4,
            "Zeit": 15,
            "Typ": "Standard"
        },
        {
            "Sorte": "Huell Melon",
            "Menge": 16,
            "Alpha": 6.4,
            "Zeit": 0,
            "Typ": "Whirlpool"
        }
    ],
    "Gewuerze_etc": [
        {
            "Name": "Koriandersamen ger\u00f6stet",
            "Menge": 11,
            "Einheit": "g",
            "Kochzeit": 15
        }
    ],
    "Stopfhopfen": [
        {
            "Sorte": "Mandarina Bavaria",
            "Menge": 35
        }
    ],
    "Hefe": "Windsor",
    "Gaertemperatur": "22 - 17",
    "Endvergaerungsgrad": 60.5,
    "Karbonisierung": 4.2,
    "Anmerkung_Autor": "Gebraut mit dem Braumeister 20.\r\nVor dem Anstellen der Hefe habe ich die Zielstammw\u00fcrze von 9,5\u00b0P mit 9,8 Liter Wasser eingestellt."
}