{
    "Rezeptquelle": "www.maischemalzundmehr.de",
    "ExportVersion": "2.0",
    "Name": "Horchamoll",
    "Datum": "27.01.2022",
    "Sorte": "Amber Ale",
    "Autor": "marsabba",
    "Ausschlagwuerze": 20,
    "Stammwuerze": 13,
    "Bittere": 32,
    "Farbe": 33,
    "Alkohol": 5.5,
    "Kurzbeschreibung": "Ein Red Ale: Tief malzig, der Hopfen h\u00e4lt sich im Hintergrund.\r\nErgab den 8. Platz beim Maisels Hobbybrauerwettbewerb 2022.",
    "Malze": [
        {
            "Name": "Wiener",
            "Menge": 2.5,
            "Einheit": "kg"
        },
        {
            "Name": "Pilsner",
            "Menge": 1,
            "Einheit": "kg"
        },
        {
            "Name": "Pale Crystal Fawcett",
            "Menge": 380,
            "Einheit": "g"
        },
        {
            "Name": "T50 Crystal Simpsons",
            "Menge": 210,
            "Einheit": "g"
        },
        {
            "Name": "Special W",
            "Menge": 88,
            "Einheit": "g"
        }
    ],
    "Maischform": "infusion",
    "Hauptguss": 16.25,
    "Einmaischtemperatur": 67,
    "Rasten": [
        {
            "Temperatur": 67,
            "Zeit": 60
        }
    ],
    "Abmaischtemperatur": 72,
    "Nachguss": 11.25,
    "Kochzeit_Wuerze": 60,
    "Hopfenkochen": [
        {
            "Sorte": "Chinook",
            "Menge": 19,
            "Alpha": 10.5,
            "Zeit": 30,
            "Typ": "Standard"
        },
        {
            "Sorte": "Callista",
            "Menge": 31,
            "Alpha": 4.4,
            "Zeit": 10,
            "Typ": "Standard"
        },
        {
            "Sorte": "Centennial",
            "Menge": 31,
            "Alpha": 9,
            "Zeit": 0,
            "Typ": "Standard"
        }
    ],
    "Hefe": "US 05",
    "Gaertemperatur": "16",
    "Endvergaerungsgrad": 77,
    "Karbonisierung": 4.5
}