{
    "Rezeptquelle": "www.maischemalzundmehr.de",
    "ExportVersion": "2.0",
    "Name": "Bitter Bliss Pale Ale",
    "Datum": "27.06.2023",
    "Sorte": "Pale Ale",
    "Autor": "B\u00e4rensteiner",
    "Ausschlagwuerze": 20,
    "Stammwuerze": 13.8,
    "Bittere": 40,
    "Farbe": 13,
    "Alkohol": 5.3,
    "Kurzbeschreibung": "Die Kombination aus den verschiedenen Hopfensorten gibt dem Bier eine angenehme Bitterkeit, die aber nicht zu stark ist. Dazu kommen fruchtige Aromen, die an Grapefruit und Zitrusfr&uuml;chte erinnern. Das macht das Pale Ale zu einem erfrischenden und gleichzeitig aromatischen Bier, das man gerne trinkt.",
    "Malze": [
        {
            "Name": "Pale Ale Malt (5.9 EBC)",
            "Menge": 4.55,
            "Einheit": "kg"
        },
        {
            "Name": "Carapils (3.9 EBC)",
            "Menge": 450,
            "Einheit": "g"
        },
        {
            "Name": "Melanoidin (70 EBC)",
            "Menge": 230,
            "Einheit": "g"
        }
    ],
    "Maischform": "infusion",
    "Hauptguss": 17.272727272727273,
    "Einmaischtemperatur": 70,
    "Rasten": [
        {
            "Temperatur": 68,
            "Zeit": 60
        }
    ],
    "Abmaischtemperatur": 78,
    "Nachguss": 10.909090909090908,
    "Kochzeit_Wuerze": 60,
    "Hopfenkochen": [
        {
            "Sorte": "Chinook",
            "Menge": 18,
            "Alpha": 11.8,
            "Zeit": 60,
            "Typ": "Standard"
        },
        {
            "Sorte": "Cascade",
            "Menge": 23,
            "Alpha": 5.5,
            "Zeit": 15,
            "Typ": "Standard"
        },
        {
            "Sorte": "Citra",
            "Menge": 23,
            "Alpha": 13.8,
            "Zeit": 5,
            "Typ": "Standard"
        }
    ],
    "Stopfhopfen": [
        {
            "Sorte": "Cascade",
            "Menge": 36
        },
        {
            "Sorte": "Chinook",
            "Menge": 36
        },
        {
            "Sorte": "Citra",
            "Menge": 36
        }
    ],
    "Hefe": "White Labs WLP001 California Ale ",
    "Gaertemperatur": "22",
    "Endvergaerungsgrad": 76,
    "Karbonisierung": 5.9,
    "Anmerkung_Autor": "Die Farbe ist ein wundersch&ouml;nes Goldgelb und der Schaum ist dicht und stabil. Der Geruch ist fruchtig und hopfig, was mich sofort auf den ersten Schluck neugierig gemacht hat.\r\n\r\nDer Geschmack ist einfach fantastisch! Die Kombination aus den verschiedenen Hopfensorten gibt dem Bier eine angenehme Bitterkeit, die aber nicht zu stark ist. Dazu kommen fruchtige Aromen, die an Grapefruit und Zitrusfr&uuml;chte erinnern. Das macht das Pale Ale zu einem erfrischenden und gleichzeitig aromatischen Bier, das man gerne trinkt.\r\n\r\nIch kann dieses Pale Ale jedem empfehlen, der gerne Bier trinkt und auf der Suche nach einem besonderen Geschmackserlebnis ist. Die Kombination aus Cascade, Chinook und Citra Hopfen ist einfach perfekt und macht das Bier zu einem echten Highlight. Probiert es aus und lasst euch von diesem tollen Bier &uuml;berraschen!\r\n\r\nWasseraufbereitung \r\n\r\nMaische:\r\n2,9g Calcium Chloride (CaCl2)\r\n2,4g Epsom Salt (MgSO4)\r\n3g Gypsum (CaSO4)\r\n\r\nNachguss:\r\n1,8g Calcium Chloride (CaCl2)\r\n1,5g Epsom Salt (MgSO4)\r\n1,9g Gypsum (CaSO4)\r\n\r\nHopfenstopfen kurz vor Ende der G&auml;rung. Ohne Hopfens&auml;ckchen etc. direkt ins Jungbier. Die G&auml;rung erfolgte unter Druck.\r\n\r\nPrim&auml;r         12 Tage bei 22&deg;C und 1,3Bar\r\nSedimentation  7 Tage bei 5&deg;C und 1,3Bar \r\nLagern         14 Tage bei -1&deg;C und 0,8Bar\r\n\r\n"
}